coinventory/__init__.py
coinventory-0.0.0.dist-info/LICENSE
coinventory-0.0.0.dist-info/METADATA
coinventory-0.0.0.dist-info/WHEEL
coinventory-0.0.0.dist-info/top_level.txt
coinventory-0.0.0.dist-info/RECORD
